eightbitdo_zero2/__init__.py
eightbitdo_zero2/eightbitdo_zero2.py
eightbitdo_zero2-0.1.3.dist-info/LICENSE
eightbitdo_zero2-0.1.3.dist-info/METADATA
eightbitdo_zero2-0.1.3.dist-info/WHEEL
eightbitdo_zero2-0.1.3.dist-info/top_level.txt
eightbitdo_zero2-0.1.3.dist-info/RECORD
