Metadata-Version: 2.1
Name: eightbitdo-zero2
Version: 0.1.3
Summary: Python code to use thev 8bitdo zero2 controller with a Raspberry Pi
Home-page: https://github.com/kawamataryo/8bitdo_zero2
Author: KawamataRyo
Author-email: ba068082@gmail.com
License: MIT
Project-URL: Homepage, https://github.com/kawamataryo/8bitdo_zero2
Project-URL: Bug Tracker, https://github.com/kawamataryo/8bitdo_zero2/issues
Keywords: 8bitdo,raspberry Pi
Classifier: Programming Language :: Python :: 3
Classifier: License :: OSI Approved :: MIT License
Classifier: Operating System :: OS Independent
Requires-Python: >=3.6
License-File: LICENSE
